tweetcal/__init__.py
tweetcal/command.py
tweetcal/read_archive.py
tweetcal/tweetcal.py
tweetcal/__pycache__/__init__.cpython-35.pyc
tweetcal/__pycache__/read_archive.cpython-35.pyc
tweetcal/__pycache__/tweetcal.cpython-35.pyc
tweetcal-0.5.2.dist-info/DESCRIPTION.rst
tweetcal-0.5.2.dist-info/METADATA
tweetcal-0.5.2.dist-info/RECORD
tweetcal-0.5.2.dist-info/WHEEL
tweetcal-0.5.2.dist-info/entry_points.txt
tweetcal-0.5.2.dist-info/metadata.json
tweetcal-0.5.2.dist-info/top_level.txt
tweetcal.egg-info/PKG-INFO
tweetcal.egg-info/SOURCES.txt
tweetcal.egg-info/dependency_links.txt
tweetcal.egg-info/entry_points.txt
tweetcal.egg-info/requires.txt
tweetcal.egg-info/top_level.txt
