Metadata-Version: 2.0
Name: tweetcal
Version: 0.5.2
Summary: Convert a tweet stream to ics calendar
Home-page: http://github.com/fitnr/tweetcal
Author: Neil Freeman
Author-email: contact@fakeisthenewreal.org
License: GPL-3.0
Platform: UNKNOWN
Classifier: Intended Audience :: Developers
Classifier: License :: OSI Approved :: GNU General Public License v3 (GPLv3)
Classifier: Natural Language :: English
Classifier: Programming Language :: Python :: 2.7
Classifier: Programming Language :: Python :: 3.4
Classifier: Operating System :: OS Independent
Requires-Dist: icalendar (>=3.8.4,<4.0)
Requires-Dist: tweepy (>=3.1.0,<4.0)
Requires-Dist: twitter-bot-utils (>=0.10.3,<1)
